py_tidy_adapter/__init__.py
py_tidy_adapter/adapter.py
py_tidy_adapter/bsc_elements.py
py_tidy_adapter/class_business.py
py_tidy_adapter/document.py
py_tidy_adapter/exception.py
py_tidy_adapter/tidy.py
py_tidy_adapter-1.1.25.dist-info/METADATA
py_tidy_adapter-1.1.25.dist-info/WHEEL
py_tidy_adapter-1.1.25.dist-info/top_level.txt
py_tidy_adapter-1.1.25.dist-info/RECORD
