Metadata-Version: 2.1
Name: py-tidy-adapter
Version: 1.1.25
Summary: python adapter to use with tidy server
Author: Michele Bassanelli
Author-email: michele.bassanelli@it-change.it
Requires-Dist: zeep
Requires-Dist: numpy
Requires-Dist: pandas
Requires-Dist: datetime
Requires-Dist: pyod
